xmodules/__init__.py
xmodules/runner.py
xmodules/session.py
xmodules/handlers/__init__.py
xmodules/handlers/calculator.py
xmodules/handlers/clear.py
xmodules/handlers/countdown.py
xmodules/handlers/flood.py
xmodules/handlers/help.py
xmodules/handlers/mention.py
xmodules/handlers/online.py
xmodules/handlers/save.py
xmodules/handlers/type.py
xmodules-1.2.0.dist-info/METADATA
xmodules-1.2.0.dist-info/WHEEL
xmodules-1.2.0.dist-info/top_level.txt
xmodules-1.2.0.dist-info/RECORD
