Metadata-Version: 2.4
Name: xmodules
Version: 1.2.0
Summary: XModules: Telegram’ingizni avtomatlashtiring, xavfsiz va oson boshqaring!
Author-email: Abdulbosit Alijonov <info@alijonov.uz>
License-Expression: MIT
Project-URL: Homepage, https://t.me/XModules
Requires-Python: >=3.8
Requires-Dist: telethon>=1.40.0
